setup.py
probability_distros/Binomialdistribution.py
probability_distros/Gaussiandistribution.py
probability_distros/Generaldistribution.py
probability_distros/__init__.py
probability_distros.egg-info/PKG-INFO
probability_distros.egg-info/SOURCES.txt
probability_distros.egg-info/dependency_links.txt
probability_distros.egg-info/not-zip-safe
probability_distros.egg-info/top_level.txt