Metadata-Version: 1.0
Name: probability-distros
Version: 0.1
Summary: Gaussian distributions
Home-page: UNKNOWN
Author: Uzodinma Ikwuakor
Author-email: uzo.ikwuakor@gmail.com
License: UNKNOWN
Platform: UNKNOWN
